aiohttp_csrf/__init__.py
aiohttp_csrf/policy.py
aiohttp_csrf/py.typed
aiohttp_csrf/storage.py
aiohttp_csrf/token_generator.py
aiohttp_csrf2-1.0.1.dist-info/LICENSE
aiohttp_csrf2-1.0.1.dist-info/METADATA
aiohttp_csrf2-1.0.1.dist-info/WHEEL
aiohttp_csrf2-1.0.1.dist-info/top_level.txt
aiohttp_csrf2-1.0.1.dist-info/RECORD
