Metadata-Version: 2.1
Name: aiohttp_csrf2
Version: 1.0.1
Summary: Cross-site request forgery (CSRF) protection for aiohttp-server
Author: TensorTom
Author-email: shuckc <chris@shucksmith.co.uk>
License: The MIT License
Project-URL: Homepage, https://github.com/shuckc/aiohttp-csrf
Keywords: asyncio,aiohttp,csrf,webserver
Classifier: Development Status :: 4 - Beta
Classifier: Intended Audience :: Developers
Classifier: Topic :: Internet :: WWW/HTTP :: HTTP Servers
Classifier: License :: OSI Approved :: MIT License
Classifier: Typing :: Typed
Classifier: Framework :: AsyncIO
Classifier: Programming Language :: Python :: 3
Classifier: Programming Language :: Python :: 3.9
Classifier: Programming Language :: Python :: 3.10
Classifier: Programming Language :: Python :: 3.11
Classifier: Programming Language :: Python :: 3.12
Requires-Python: >=3.9
License-File: LICENSE
Requires-Dist: blake3 >=0.4.1
Requires-Dist: aiohttp >=3.10.0
Requires-Dist: aiohttp-session >=2.12.0
